microsoft_agents/hosting/aiohttp/__init__.py
microsoft_agents/hosting/aiohttp/_start_agent_process.py
microsoft_agents/hosting/aiohttp/agent_http_adapter.py
microsoft_agents/hosting/aiohttp/channel_service_route_table.py
microsoft_agents/hosting/aiohttp/cloud_adapter.py
microsoft_agents/hosting/aiohttp/jwt_authorization_middleware.py
microsoft_agents/hosting/aiohttp/app/__init__.py
microsoft_agents/hosting/aiohttp/app/streaming/__init__.py
microsoft_agents/hosting/aiohttp/app/streaming/citation.py
microsoft_agents/hosting/aiohttp/app/streaming/citation_util.py
microsoft_agents/hosting/aiohttp/app/streaming/streaming_response.py
microsoft_agents_hosting_aiohttp-0.7.0.dist-info/licenses/LICENSE
microsoft_agents_hosting_aiohttp-0.7.0.dist-info/METADATA
microsoft_agents_hosting_aiohttp-0.7.0.dist-info/WHEEL
microsoft_agents_hosting_aiohttp-0.7.0.dist-info/top_level.txt
microsoft_agents_hosting_aiohttp-0.7.0.dist-info/RECORD
